amcp/__init__.py
amcp-0.0.2.dist-info/licenses/LICENSE
amcp-0.0.2.dist-info/METADATA
amcp-0.0.2.dist-info/WHEEL
amcp-0.0.2.dist-info/top_level.txt
amcp-0.0.2.dist-info/RECORD
