Metadata-Version: 2.4
Name: amcp
Version: 0.0.2
Summary: Python SDK for automcp.ai - Generate MCP servers from OpenAPI specifications
Author-email: "automcp.ai team" <gavin@automcp.ai>
License: MIT
Project-URL: Homepage, https://automcp.ai
Project-URL: Documentation, https://github.com/automcp-ai/amcp
Project-URL: Repository, https://github.com/automcp-ai/amcp
Project-URL: Issues, https://github.com/automcp-ai/amcp/issues
Project-URL: Main Project, https://automcp.ai
Keywords: mcp,openapi,api,sdk,automation,model-context-protocol
Classifier: Development Status :: 1 - Planning
Classifier: Intended Audience :: Developers
Classifier: License :: OSI Approved :: MIT License
Classifier: Programming Language :: Python :: 3
Classifier: Programming Language :: Python :: 3.8
Classifier: Programming Language :: Python :: 3.9
Classifier: Programming Language :: Python :: 3.10
Classifier: Programming Language :: Python :: 3.11
Classifier: Programming Language :: Python :: 3.12
Classifier: Programming Language :: Python :: 3.13
Classifier: Topic :: Software Development :: Libraries :: Python Modules
Classifier: Topic :: Software Development :: Code Generators
Requires-Python: >=3.8
License-File: LICENSE
Dynamic: license-file
